skaf/__init__.py
skaf/cli.py
skaf/properties.py
skaf/registry.py
skaf/scaffold/__init__.py
skaf/scaffold/context.py
skaf/scaffold/scaffold.py
skaf/scaffold/utils.py
skaf/scaffold/variables.py
skaf/template_classes/__init__.py
skaf/template_classes/_none.py
skaf/template_classes/base.py
skaf/template_classes/dict_template.py
skaf/template_classes/filesystem_template.py
skaf/template_classes/git_template.py
skaf/template_lib/setuptools_pyproject/template_properties.yaml
skaf/template_lib/setuptools_pyproject/template/ README.md.jinja
skaf/template_lib/setuptools_pyproject/template/LICENSE
skaf/template_lib/setuptools_pyproject/template/pyproject.toml.jinja
skaf/template_lib/setuptools_pyproject/template/src/{{ project_name }}/__init__.py
skaf/template_lib/setuptools_pyproject/template/src/{{ project_name }}/main.py
skaf/template_lib/setuptools_pyproject/template/test/test_main.py.jinja
skaf/templaters/__init__.py
skaf/templaters/base.py
skaf/templaters/jinja.py
skaf/templaters/pystring.py
skaf/templaters/registry.py
skaf-0.1.6.dist-info/METADATA
skaf-0.1.6.dist-info/WHEEL
skaf-0.1.6.dist-info/entry_points.txt
skaf-0.1.6.dist-info/top_level.txt
skaf-0.1.6.dist-info/RECORD
