Metadata-Version: 2.4
Name: skaf
Version: 0.1.6
Summary: A tool to scaffold projects from templates
Author-email: John Raines <johndanielraines@gmail.com>
Project-URL: Homepage, https://github.com/jdraines/skaf
Project-URL: Documentation, https://github.com/jdraines/skaf/blob/main/README.md
Project-URL: Repository, https://github.com/jdraines/skaf
Classifier: Development Status :: 4 - Beta
Classifier: Intended Audience :: Developers
Classifier: Topic :: Software Development
Classifier: License :: OSI Approved :: MIT License
Classifier: Programming Language :: Python :: 3
Classifier: Programming Language :: Python :: 3.10
Classifier: Programming Language :: Python :: 3.11
Classifier: Programming Language :: Python :: 3.12
Requires-Python: >=3.10
Requires-Dist: pyyaml>=6.0
Requires-Dist: Jinja2==3.1.6
Requires-Dist: GitPython==3.1.44
Provides-Extra: dev
Requires-Dist: pytest; extra == "dev"
Requires-Dist: pytest-cov; extra == "dev"
